NetTrade/__init__.py
NetTrade/ExcelDataUtil/__init__.py
NetTrade/ExcelDataUtil/headers.py
NetTrade/ExcelDataUtil/xlsxDataGetter.py
NetTrade/ExcelDataUtil/xlsxDataWriter.py
NetTrade/HistoryNotes/HistoryNotes.py
NetTrade/HistoryNotes/__init__.py
NetTrade/Notes/RealNotes.py
NetTrade/Notes/__init__.py
NetTrade/Strategy/NetstrategyA.py
NetTrade/Strategy/__init__.py
NetTrade/TestDataUtil/DataGetter.py
NetTrade/TestDataUtil/GetterFactory.py
NetTrade/TestDataUtil/JSLGetter.py
NetTrade/TestDataUtil/__init__.py
NetTrade/Util/__init__.py
NetTrade/Util/dateUtil.py
NetTrade/Variables/Status.py
NetTrade/Variables/__init__.py
NetTrade-1.0.3.dist-info/LICENSE
NetTrade-1.0.3.dist-info/WHEEL
NetTrade-1.0.3.dist-info/METADATA
NetTrade-1.0.3.dist-info/RECORD
